{
  "fetched_at": "2026-07-09T11:49:57.872536+00:00",
  "location": {
    "name": "Wausau, WI",
    "lat": 44.9591,
    "lng": -89.6301,
    "nws_office": "GRB",
    "nws_grid": [
      25,
      50
    ],
    "observation_station": "KCWA"
  },
  "precipitation": {
    "last_24h_in": 0.02,
    "last_72h_in": 0.02
  },
  "forecast": {
    "periods": [
      {
        "name": "Today",
        "start_time": "2026-07-09T06:00:00-05:00",
        "end_time": "2026-07-09T18:00:00-05:00",
        "is_daytime": true,
        "temp_f": 81,
        "wind_mph_low": 6.0,
        "wind_mph_high": 6.0,
        "precip_chance": 26,
        "short_forecast": "Chance Rain Showers then Slight Chance Showers And Thunderstorms"
      },
      {
        "name": "Tonight",
        "start_time": "2026-07-09T18:00:00-05:00",
        "end_time": "2026-07-10T06:00:00-05:00",
        "is_daytime": false,
        "temp_f": 59,
        "wind_mph_low": 5.0,
        "wind_mph_high": 5.0,
        "precip_chance": 6,
        "short_forecast": "Patchy Fog"
      },
      {
        "name": "Friday",
        "start_time": "2026-07-10T06:00:00-05:00",
        "end_time": "2026-07-10T18:00:00-05:00",
        "is_daytime": true,
        "temp_f": 83,
        "wind_mph_low": 5.0,
        "wind_mph_high": 5.0,
        "precip_chance": 0,
        "short_forecast": "Areas Of Fog then Mostly Sunny"
      },
      {
        "name": "Friday Night",
        "start_time": "2026-07-10T18:00:00-05:00",
        "end_time": "2026-07-11T06:00:00-05:00",
        "is_daytime": false,
        "temp_f": 61,
        "wind_mph_low": 3.0,
        "wind_mph_high": 3.0,
        "precip_chance": 4,
        "short_forecast": "Mostly Clear"
      }
    ]
  },
  "scoring_context": {
    "recent_precip_in_24h": 0.02,
    "recent_precip_in_72h": 0.02,
    "forecast_temp_f": 81,
    "forecast_wind_mph": 6.0,
    "forecast_precip_chance": 26,
    "daylight_remaining_minutes": 825,
    "active_closure_ids": []
  }
}