{
  "id": "osm-iat---white-cedar-ringle-connector",
  "name": "IAT - White Cedar-Ringle connector",
  "activities": [
    "hiking"
  ],
  "sources": {
    "osm": {
      "relation_id": 19693063,
      "last_fetched": ""
    }
  },
  "geometry": {
    "type": "LineString",
    "coordinates": [
      [
        -89.3438076,
        44.8780378
      ],
      [
        -89.3441864,
        44.8780354
      ],
      [
        -89.3441685,
        44.8774
      ],
      [
        -89.3441417,
        44.8767918
      ],
      [
        -89.3441578,
        44.8766322
      ],
      [
        -89.3441954,
        44.8764269
      ],
      [
        -89.3443456,
        44.8760049
      ],
      [
        -89.345166,
        44.874011
      ],
      [
        -89.345219,
        44.873832
      ],
      [
        -89.3452393,
        44.8737559
      ],
      [
        -89.34532,
        44.873454
      ],
      [
        -89.345379,
        44.873186
      ],
      [
        -89.345681,
        44.871955
      ],
      [
        -89.345857,
        44.871196
      ],
      [
        -89.345963,
        44.870813
      ],
      [
        -89.346125,
        44.870153
      ],
      [
        -89.346187,
        44.869919
      ],
      [
        -89.346301,
        44.869424
      ],
      [
        -89.34644,
        44.868903
      ],
      [
        -89.346501,
        44.868628
      ],
      [
        -89.346587,
        44.868275
      ],
      [
        -89.346664,
        44.867982
      ],
      [
        -89.346682,
        44.867915
      ],
      [
        -89.346726,
        44.867741
      ],
      [
        -89.346786,
        44.86746
      ],
      [
        -89.346849,
        44.867238
      ],
      [
        -89.346905,
        44.867078
      ],
      [
        -89.347057,
        44.866723
      ],
      [
        -89.347186,
        44.866489
      ],
      [
        -89.347363,
        44.866244
      ],
      [
        -89.347505,
        44.866075
      ],
      [
        -89.347752,
        44.865807
      ],
      [
        -89.348124,
        44.865389
      ],
      [
        -89.348605,
        44.864879
      ],
      [
        -89.348852,
        44.864609
      ],
      [
        -89.349683,
        44.863722
      ],
      [
        -89.349881,
        44.8635
      ],
      [
        -89.350417,
        44.86292
      ],
      [
        -89.35077,
        44.862527
      ],
      [
        -89.351074,
        44.862221
      ],
      [
        -89.351254,
        44.862013
      ],
      [
        -89.35136,
        44.861869
      ],
      [
        -89.351456,
        44.861722
      ],
      [
        -89.351577,
        44.861494
      ],
      [
        -89.351636,
        44.861347
      ],
      [
        -89.351702,
        44.861124
      ],
      [
        -89.351749,
        44.861008
      ],
      [
        -89.351758,
        44.860823
      ],
      [
        -89.351736,
        44.858998
      ],
      [
        -89.351715,
        44.856436
      ],
      [
        -89.351724,
        44.85434
      ],
      [
        -89.35177,
        44.849723
      ],
      [
        -89.351769,
        44.848951
      ],
      [
        -89.351762,
        44.846258
      ],
      [
        -89.351736,
        44.841712
      ],
      [
        -89.350424,
        44.84165
      ],
      [
        -89.349344,
        44.841608
      ],
      [
        -89.348951,
        44.841582
      ],
      [
        -89.347425,
        44.8415
      ],
      [
        -89.347057,
        44.841486
      ],
      [
        -89.34664,
        44.841484
      ],
      [
        -89.346627,
        44.841395
      ],
      [
        -89.346609,
        44.840453
      ],
      [
        -89.346597,
        44.840113
      ],
      [
        -89.346587,
        44.839604
      ],
      [
        -89.346568,
        44.839183
      ],
      [
        -89.346564,
        44.838832
      ],
      [
        -89.346536,
        44.837654
      ],
      [
        -89.346543,
        44.837288
      ],
      [
        -89.346536,
        44.836691
      ],
      [
        -89.346512,
        44.83603
      ],
      [
        -89.3465094,
        44.8358525
      ]
    ]
  },
  "attributes": {
    "length_m": 5217.3,
    "elevation_gain_m": 26.4,
    "elevation_max_m": 391.1,
    "elevation_min_m": 380.5,
    "elevation_profile": [
      [
        0.0,
        388.4
      ],
      [
        75.9,
        388.1
      ],
      [
        175.7,
        388.0
      ],
      [
        275.7,
        387.4
      ],
      [
        375.7,
        386.9
      ],
      [
        475.6,
        384.8
      ],
      [
        575.6,
        384.1
      ],
      [
        675.6,
        384.7
      ],
      [
        775.6,
        384.5
      ],
      [
        875.6,
        384.2
      ],
      [
        975.6,
        384.7
      ],
      [
        1075.6,
        386.1
      ],
      [
        1175.6,
        387.2
      ],
      [
        1275.4,
        390.9
      ],
      [
        1375.0,
        391.1
      ],
      [
        1475.0,
        387.7
      ],
      [
        1575.0,
        387.6
      ],
      [
        1675.0,
        387.5
      ],
      [
        1775.0,
        386.2
      ],
      [
        1875.0,
        385.4
      ],
      [
        1974.6,
        385.0
      ],
      [
        2073.9,
        385.9
      ],
      [
        2173.9,
        387.8
      ],
      [
        2273.9,
        387.9
      ],
      [
        2373.9,
        389.8
      ],
      [
        2473.9,
        390.3
      ],
      [
        2573.9,
        390.5
      ],
      [
        2673.9,
        390.3
      ],
      [
        2773.9,
        385.5
      ],
      [
        2873.9,
        384.3
      ],
      [
        2973.9,
        389.0
      ],
      [
        3073.9,
        389.5
      ],
      [
        3173.9,
        390.0
      ],
      [
        3273.9,
        389.4
      ],
      [
        3373.9,
        387.2
      ],
      [
        3473.9,
        384.1
      ],
      [
        3573.9,
        383.7
      ],
      [
        3673.9,
        383.1
      ],
      [
        3773.9,
        383.5
      ],
      [
        3873.9,
        383.5
      ],
      [
        3973.9,
        381.6
      ],
      [
        4073.9,
        383.3
      ],
      [
        4171.6,
        384.1
      ],
      [
        4271.6,
        385.1
      ],
      [
        4371.6,
        387.1
      ],
      [
        4471.6,
        386.6
      ],
      [
        4571.5,
        386.7
      ],
      [
        4671.4,
        384.9
      ],
      [
        4771.4,
        382.9
      ],
      [
        4871.3,
        384.4
      ],
      [
        4971.3,
        383.0
      ],
      [
        5071.3,
        383.1
      ],
      [
        5171.3,
        380.9
      ],
      [
        5197.8,
        380.5
      ]
    ],
    "difficulty_estimated": "moderate",
    "surface": [],
    "is_loop": false,
    "osm_network_class": "nwn",
    "blaze_color": null,
    "counties": [
      "marathon"
    ],
    "park": null,
    "managing_authority": "Unknown"
  },
  "editorial": {},
  "derived": {
    "centroid": [
      -89.34901661677728,
      44.85598082164107
    ],
    "bbox": [
      -89.35177,
      44.8358525,
      -89.3438076,
      44.8780378
    ],
    "drive_minutes_from_wausau": 24,
    "trailhead_coords": [
      -89.3465094,
      44.8358525
    ],
    "parking_distance_m": 46
  }
}