{
  "id": "osmway-flambeau-atv-trail-101",
  "name": "Flambeau ATV Trail 101",
  "activities": [
    "atv",
    "utv"
  ],
  "sources": {
    "osm": {
      "way_ids": [
        21557000,
        21557011,
        21557312,
        1255039065,
        1309855211
      ],
      "kind": "named_way",
      "last_fetched": ""
    }
  },
  "geometry": {
    "type": "LineString",
    "coordinates": [
      [
        -90.2797428,
        45.9039703
      ],
      [
        -90.2796548,
        45.9040742
      ],
      [
        -90.2794451,
        45.9042091
      ],
      [
        -90.2791061,
        45.9043311
      ],
      [
        -90.2785281,
        45.9049376
      ],
      [
        -90.2783014,
        45.905188
      ],
      [
        -90.2782621,
        45.9052822
      ],
      [
        -90.2782132,
        45.9053585
      ],
      [
        -90.2781551,
        45.9054408
      ],
      [
        -90.2780644,
        45.9054909
      ],
      [
        -90.2779297,
        45.9055228
      ],
      [
        -90.2778151,
        45.9055552
      ],
      [
        -90.2776662,
        45.9055637
      ],
      [
        -90.2773526,
        45.9055311
      ],
      [
        -90.2772357,
        45.9055491
      ],
      [
        -90.2771287,
        45.9055831
      ],
      [
        -90.2769422,
        45.905666
      ],
      [
        -90.2768357,
        45.9057382
      ],
      [
        -90.2767037,
        45.9057729
      ],
      [
        -90.2765127,
        45.9057804
      ],
      [
        -90.2760922,
        45.9058256
      ],
      [
        -90.2757013,
        45.90583
      ],
      [
        -90.2754603,
        45.905709
      ],
      [
        -90.2751302,
        45.905623
      ],
      [
        -90.2748012,
        45.9055888
      ],
      [
        -90.2744343,
        45.9055427
      ],
      [
        -90.2742736,
        45.9055322
      ],
      [
        -90.2739835,
        45.9056155
      ],
      [
        -90.2737332,
        45.9056754
      ],
      [
        -90.2735801,
        45.905772
      ],
      [
        -90.2734523,
        45.9059811
      ],
      [
        -90.2733643,
        45.9061458
      ],
      [
        -90.2733099,
        45.9063177
      ],
      [
        -90.273291,
        45.9064332
      ],
      [
        -90.2732689,
        45.9065445
      ],
      [
        -90.2731211,
        45.9066795
      ],
      [
        -90.272906,
        45.906833
      ],
      [
        -90.2728152,
        45.9070043
      ],
      [
        -90.2726586,
        45.9072193
      ],
      [
        -90.2723116,
        45.9075374
      ],
      [
        -90.2719431,
        45.9077714
      ],
      [
        -90.2715303,
        45.9079101
      ],
      [
        -90.2709485,
        45.9080241
      ],
      [
        -90.270754,
        45.9081036
      ],
      [
        -90.2706106,
        45.9081912
      ],
      [
        -90.2705107,
        45.9083033
      ],
      [
        -90.2703576,
        45.9084017
      ],
      [
        -90.2702073,
        45.9084543
      ],
      [
        -90.2700159,
        45.9085219
      ],
      [
        -90.2696939,
        45.9086134
      ],
      [
        -90.2693914,
        45.9086655
      ],
      [
        -90.2691795,
        45.9087203
      ],
      [
        -90.2689928,
        45.9087906
      ],
      [
        -90.2686405,
        45.9089303
      ],
      [
        -90.2681602,
        45.9090653
      ],
      [
        -90.2679502,
        45.9091049
      ],
      [
        -90.2678099,
        45.9090773
      ],
      [
        -90.2676794,
        45.9090307
      ],
      [
        -90.2674113,
        45.9089516
      ],
      [
        -90.26719,
        45.9088897
      ],
      [
        -90.2670265,
        45.9088487
      ],
      [
        -90.2668848,
        45.9088643
      ],
      [
        -90.2667507,
        45.9089129
      ],
      [
        -90.266475,
        45.9089078
      ],
      [
        -90.2662347,
        45.9088511
      ],
      [
        -90.2660496,
        45.9088511
      ],
      [
        -90.2634998,
        45.9095977
      ],
      [
        -90.2631422,
        45.9096065
      ],
      [
        -90.2629264,
        45.909578
      ],
      [
        -90.2627524,
        45.9095446
      ],
      [
        -90.2626224,
        45.9094416
      ],
      [
        -90.2624269,
        45.9093307
      ],
      [
        -90.2621074,
        45.9091905
      ],
      [
        -90.2619996,
        45.9090335
      ],
      [
        -90.2619089,
        45.9088709
      ],
      [
        -90.2617466,
        45.908801
      ],
      [
        -90.2611384,
        45.9086926
      ],
      [
        -90.2607379,
        45.9086376
      ],
      [
        -90.2603696,
        45.908627
      ],
      [
        -90.2601105,
        45.908623
      ],
      [
        -90.2599033,
        45.9085986
      ],
      [
        -90.2596754,
        45.9085279
      ],
      [
        -90.2591454,
        45.9082172
      ],
      [
        -90.258921,
        45.9081157
      ],
      [
        -90.2586457,
        45.9080068
      ],
      [
        -90.2584177,
        45.9079091
      ],
      [
        -90.2584082,
        45.9078351
      ],
      [
        -90.2583482,
        45.9076823
      ],
      [
        -90.2582347,
        45.9075292
      ],
      [
        -90.2580763,
        45.9074689
      ],
      [
        -90.2579236,
        45.9073993
      ],
      [
        -90.257834,
        45.9072738
      ],
      [
        -90.2574887,
        45.9072006
      ],
      [
        -90.257067,
        45.9071128
      ],
      [
        -90.2568145,
        45.9069883
      ],
      [
        -90.2564549,
        45.9069196
      ],
      [
        -90.256042,
        45.9068601
      ],
      [
        -90.2557716,
        45.9069691
      ],
      [
        -90.2553872,
        45.9070979
      ],
      [
        -90.254889,
        45.9071177
      ],
      [
        -90.2540918,
        45.9069988
      ],
      [
        -90.2533942,
        45.9068601
      ],
      [
        -90.2523408,
        45.9068304
      ],
      [
        -90.2521915,
        45.9067626
      ],
      [
        -90.2520134,
        45.9066818
      ],
      [
        -90.2513301,
        45.906454
      ],
      [
        -90.2509315,
        45.9065134
      ],
      [
        -90.2504475,
        45.906563
      ],
      [
        -90.24975,
        45.9065432
      ],
      [
        -90.2489528,
        45.9067116
      ],
      [
        -90.2482552,
        45.9071078
      ],
      [
        -90.247999,
        45.9071672
      ],
      [
        -90.2474153,
        45.907088
      ],
      [
        -90.2469028,
        45.907088
      ],
      [
        -90.2466893,
        45.9068601
      ],
      [
        -90.2466181,
        45.9066125
      ],
      [
        -90.2462195,
        45.9064144
      ],
      [
        -90.2456359,
        45.9061469
      ],
      [
        -90.2447818,
        45.906038
      ],
      [
        -90.2441839,
        45.9059885
      ],
      [
        -90.2435006,
        45.9058399
      ],
      [
        -90.2430735,
        45.9056021
      ],
      [
        -90.2424471,
        45.9053248
      ],
      [
        -90.2417496,
        45.905087
      ],
      [
        -90.2414222,
        45.9046908
      ],
      [
        -90.2407816,
        45.9042748
      ],
      [
        -90.2404257,
        45.9039776
      ],
      [
        -90.2398847,
        45.90372
      ],
      [
        -90.239358,
        45.9035318
      ],
      [
        -90.2391422,
        45.9035308
      ],
      [
        -90.2388598,
        45.903512
      ],
      [
        -90.2385039,
        45.9036408
      ],
      [
        -90.2378206,
        45.9035813
      ],
      [
        -90.2370946,
        45.9034922
      ],
      [
        -90.2365963,
        45.9036507
      ],
      [
        -90.2362405,
        45.9038884
      ],
      [
        -90.2358988,
        45.9041163
      ],
      [
        -90.2353151,
        45.9041163
      ],
      [
        -90.2346888,
        45.904146
      ],
      [
        -90.234219,
        45.903829
      ],
      [
        -90.234034,
        45.9037002
      ],
      [
        -90.2336638,
        45.9036309
      ],
      [
        -90.2333791,
        45.9036309
      ],
      [
        -90.2330659,
        45.9037002
      ],
      [
        -90.2326104,
        45.9037596
      ],
      [
        -90.2322545,
        45.9037398
      ],
      [
        -90.2318417,
        45.9038785
      ],
      [
        -90.2312153,
        45.9039578
      ],
      [
        -90.2307313,
        45.9038389
      ],
      [
        -90.2303185,
        45.9037002
      ],
      [
        -90.2298345,
        45.9036012
      ],
      [
        -90.2291654,
        45.9035912
      ],
      [
        -90.228881,
        45.903523
      ],
      [
        -90.22868,
        45.9034583
      ],
      [
        -90.2284995,
        45.9034221
      ],
      [
        -90.2283824,
        45.9033534
      ],
      [
        -90.228249,
        45.9031329
      ],
      [
        -90.2281718,
        45.9027763
      ],
      [
        -90.228193,
        45.9023934
      ],
      [
        -90.228066,
        45.9021578
      ],
      [
        -90.227939,
        45.9019221
      ],
      [
        -90.227939,
        45.9016129
      ],
      [
        -90.2277909,
        45.901392
      ],
      [
        -90.2276851,
        45.9011858
      ],
      [
        -90.2277909,
        45.9009944
      ],
      [
        -90.227939,
        45.9008176
      ],
      [
        -90.2280237,
        45.900582
      ],
      [
        -90.2280237,
        45.9003022
      ],
      [
        -90.2281718,
        45.9000077
      ],
      [
        -90.2283411,
        45.8998015
      ],
      [
        -90.2285316,
        45.8995658
      ],
      [
        -90.2285527,
        45.899286
      ],
      [
        -90.2285501,
        45.8989947
      ],
      [
        -90.2285398,
        45.8988192
      ],
      [
        -90.2285707,
        45.898658
      ],
      [
        -90.2285604,
        45.8984539
      ],
      [
        -90.2285758,
        45.8982534
      ],
      [
        -90.2285655,
        45.8981065
      ],
      [
        -90.2285861,
        45.8979955
      ],
      [
        -90.2285861,
        45.897863
      ],
      [
        -90.2285501,
        45.8977377
      ],
      [
        -90.2284472,
        45.8976589
      ],
      [
        -90.2281301,
        45.8974925
      ],
      [
        -90.2276708,
        45.8971856
      ],
      [
        -90.2271564,
        45.8970066
      ],
      [
        -90.2265318,
        45.8968532
      ],
      [
        -90.2261092,
        45.8966742
      ],
      [
        -90.2255764,
        45.8964185
      ],
      [
        -90.2251906,
        45.8962139
      ],
      [
        -90.2249334,
        45.8959838
      ],
      [
        -90.2246211,
        45.8958559
      ],
      [
        -90.2240883,
        45.8956641
      ],
      [
        -90.2234821,
        45.8955874
      ],
      [
        -90.2228758,
        45.895549
      ],
      [
        -90.222343,
        45.8956513
      ],
      [
        -90.2220123,
        45.8957025
      ],
      [
        -90.2217,
        45.8959326
      ],
      [
        -90.2214244,
        45.8962906
      ],
      [
        -90.2210202,
        45.8966231
      ],
      [
        -90.2207814,
        45.8967893
      ],
      [
        -90.2203405,
        45.8968532
      ],
      [
        -90.2200282,
        45.8967765
      ],
      [
        -90.2194586,
        45.8967381
      ],
      [
        -90.2189626,
        45.8967381
      ],
      [
        -90.2185024,
        45.8967668
      ],
      [
        -90.2178452,
        45.8969251
      ],
      [
        -90.217161,
        45.8969072
      ],
      [
        -90.2167428,
        45.8968402
      ],
      [
        -90.2157458,
        45.896471
      ],
      [
        -90.2151104,
        45.8962686
      ],
      [
        -90.2145783,
        45.8962315
      ],
      [
        -90.214279,
        45.8962642
      ],
      [
        -90.2135403,
        45.8963716
      ],
      [
        -90.2118955,
        45.896202
      ],
      [
        -90.2112873,
        45.8961443
      ],
      [
        -90.2108702,
        45.8963082
      ],
      [
        -90.2104883,
        45.8964426
      ],
      [
        -90.21014,
        45.8965186
      ],
      [
        -90.2091463,
        45.8965401
      ],
      [
        -90.2088394,
        45.8965431
      ],
      [
        -90.2082577,
        45.8965117
      ],
      [
        -90.2075561,
        45.8963717
      ],
      [
        -90.2052768,
        45.8963199
      ],
      [
        -90.2048194,
        45.896273
      ],
      [
        -90.204143,
        45.8961205
      ],
      [
        -90.203334,
        45.895814
      ],
      [
        -90.20281,
        45.895495
      ],
      [
        -90.201338,
        45.895152
      ],
      [
        -90.1988971,
        45.8944243
      ],
      [
        -90.1980797,
        45.8941217
      ],
      [
        -90.1976721,
        45.8939604
      ],
      [
        -90.1974039,
        45.8938748
      ],
      [
        -90.196873,
        45.8938442
      ],
      [
        -90.1960997,
        45.8938909
      ],
      [
        -90.1951228,
        45.8938257
      ],
      [
        -90.1944061,
        45.8939144
      ],
      [
        -90.1940116,
        45.8939834
      ],
      [
        -90.1938696,
        45.8939632
      ],
      [
        -90.1933121,
        45.8937776
      ],
      [
        -90.1931304,
        45.8937798
      ],
      [
        -90.1929262,
        45.8938624
      ],
      [
        -90.191391,
        45.894627
      ],
      [
        -90.190736,
        45.894513
      ],
      [
        -90.190507,
        45.894627
      ],
      [
        -90.190016,
        45.895335
      ],
      [
        -90.1890533,
        45.8954929
      ],
      [
        -90.1878627,
        45.8958465
      ],
      [
        -90.1876854,
        45.8959521
      ],
      [
        -90.1874963,
        45.8961744
      ],
      [
        -90.187324,
        45.8964545
      ],
      [
        -90.1872496,
        45.8966956
      ],
      [
        -90.18694,
        45.897186
      ],
      [
        -90.186584,
        45.8973587
      ],
      [
        -90.1862242,
        45.8973874
      ],
      [
        -90.185782,
        45.8975052
      ],
      [
        -90.1854435,
        45.8976427
      ],
      [
        -90.1851714,
        45.8976939
      ],
      [
        -90.1848568,
        45.8978632
      ],
      [
        -90.1844505,
        45.8980433
      ],
      [
        -90.1841618,
        45.8982106
      ],
      [
        -90.1839156,
        45.8984581
      ],
      [
        -90.1836834,
        45.8987483
      ],
      [
        -90.1834338,
        45.8989155
      ],
      [
        -90.1832176,
        45.8990215
      ],
      [
        -90.18296,
        45.8990634
      ],
      [
        -90.1820731,
        45.8990888
      ],
      [
        -90.181247,
        45.8991394
      ],
      [
        -90.1810691,
        45.8991181
      ],
      [
        -90.1809713,
        45.8991064
      ],
      [
        -90.1803879,
        45.8988544
      ],
      [
        -90.179787,
        45.8986547
      ],
      [
        -90.1792563,
        45.8985548
      ],
      [
        -90.1789388,
        45.8984475
      ],
      [
        -90.1786752,
        45.8983081
      ],
      [
        -90.1784359,
        45.8982456
      ],
      [
        -90.1781648,
        45.898247
      ],
      [
        -90.17761,
        45.8982723
      ],
      [
        -90.1772515,
        45.8981987
      ],
      [
        -90.1770165,
        45.8981503
      ],
      [
        -90.1767281,
        45.898147
      ],
      [
        -90.1765391,
        45.8982039
      ],
      [
        -90.1762614,
        45.8983479
      ],
      [
        -90.1760319,
        45.8984301
      ],
      [
        -90.1757598,
        45.8985077
      ],
      [
        -90.1752226,
        45.8988348
      ],
      [
        -90.1750134,
        45.8989104
      ],
      [
        -90.1746991,
        45.8988962
      ],
      [
        -90.173164,
        45.898602
      ],
      [
        -90.1728685,
        45.8985791
      ],
      [
        -90.1726911,
        45.8986428
      ],
      [
        -90.1725789,
        45.8987164
      ],
      [
        -90.1718252,
        45.8993262
      ],
      [
        -90.1716713,
        45.8994149
      ],
      [
        -90.1711377,
        45.8995713
      ],
      [
        -90.1707446,
        45.8997498
      ],
      [
        -90.1703718,
        45.8999731
      ],
      [
        -90.1696789,
        45.9003422
      ],
      [
        -90.169088,
        45.9005451
      ],
      [
        -90.1688055,
        45.9006132
      ],
      [
        -90.1686589,
        45.9006015
      ],
      [
        -90.1684437,
        45.9005364
      ],
      [
        -90.1681862,
        45.9004319
      ],
      [
        -90.1681091,
        45.9003144
      ],
      [
        -90.1680642,
        45.9001419
      ],
      [
        -90.1681562,
        45.8999664
      ],
      [
        -90.1682564,
        45.8998314
      ],
      [
        -90.1683961,
        45.8996628
      ],
      [
        -90.1685725,
        45.8994613
      ],
      [
        -90.1687176,
        45.8993343
      ],
      [
        -90.1687848,
        45.8991969
      ],
      [
        -90.1687656,
        45.8990581
      ],
      [
        -90.1689433,
        45.8985827
      ],
      [
        -90.1688776,
        45.8982541
      ],
      [
        -90.1688462,
        45.8979542
      ],
      [
        -90.1685656,
        45.8975328
      ],
      [
        -90.1683574,
        45.8973526
      ],
      [
        -90.1680661,
        45.8971484
      ],
      [
        -90.167808,
        45.897066
      ],
      [
        -90.1672938,
        45.8970004
      ],
      [
        -90.1669031,
        45.8969824
      ],
      [
        -90.1662089,
        45.8967815
      ],
      [
        -90.1497621,
        45.8968205
      ],
      [
        -90.1447041,
        45.8968618
      ],
      [
        -90.1377768,
        45.8969184
      ],
      [
        -90.135403,
        45.8969306
      ],
      [
        -90.129022,
        45.896965
      ],
      [
        -90.125814,
        45.896955
      ],
      [
        -90.125157,
        45.896953
      ],
      [
        -90.114653,
        45.896858
      ],
      [
        -90.110791,
        45.896905
      ],
      [
        -90.0889,
        45.896958
      ],
      [
        -90.0841467,
        45.896959
      ]
    ]
  },
  "attributes": {
    "length_m": 17522.5,
    "elevation_gain_m": 103.1,
    "elevation_max_m": 478.7,
    "elevation_min_m": 460.7,
    "elevation_profile": [
      [
        0.0,
        471.2
      ],
      [
        97.5,
        471.1
      ],
      [
        197.0,
        469.0
      ],
      [
        290.4,
        474.0
      ],
      [
        387.3,
        473.8
      ],
      [
        485.1,
        472.9
      ],
      [
        577.1,
        467.0
      ],
      [
        675.2,
        470.2
      ],
      [
        774.0,
        467.3
      ],
      [
        871.9,
        464.8
      ],
      [
        968.6,
        464.6
      ],
      [
        1068.2,
        465.8
      ],
      [
        1167.7,
        464.1
      ],
      [
        1263.1,
        465.7
      ],
      [
        1359.1,
        465.6
      ],
      [
        1459.1,
        465.7
      ],
      [
        1557.4,
        465.3
      ],
      [
        1653.8,
        463.6
      ],
      [
        1745.5,
        466.4
      ],
      [
        1844.8,
        471.4
      ],
      [
        1944.3,
        472.6
      ],
      [
        2037.8,
        464.3
      ],
      [
        2133.5,
        460.7
      ],
      [
        2226.8,
        463.3
      ],
      [
        2323.8,
        463.9
      ],
      [
        2423.3,
        464.9
      ],
      [
        2520.2,
        467.1
      ],
      [
        2615.2,
        467.3
      ],
      [
        2714.2,
        467.3
      ],
      [
        2812.4,
        468.9
      ],
      [
        2908.8,
        470.5
      ],
      [
        2999.1,
        469.9
      ],
      [
        3097.2,
        467.8
      ],
      [
        3196.9,
        466.1
      ],
      [
        3295.6,
        466.4
      ],
      [
        3394.6,
        466.5
      ],
      [
        3493.5,
        466.2
      ],
      [
        3592.7,
        465.6
      ],
      [
        3688.0,
        465.3
      ],
      [
        3784.8,
        470.3
      ],
      [
        3878.2,
        469.6
      ],
      [
        3971.1,
        467.7
      ],
      [
        4062.6,
        469.9
      ],
      [
        4156.6,
        475.9
      ],
      [
        4254.4,
        477.8
      ],
      [
        4350.6,
        476.4
      ],
      [
        4449.3,
        478.7
      ],
      [
        4541.9,
        477.9
      ],
      [
        4640.8,
        475.6
      ],
      [
        4739.1,
        474.0
      ],
      [
        4834.1,
        473.0
      ],
      [
        4932.0,
        474.0
      ],
      [
        5030.1,
        472.3
      ],
      [
        5129.8,
        472.3
      ],
      [
        5225.3,
        470.9
      ],
      [
        5324.4,
        470.4
      ],
      [
        5424.1,
        471.0
      ],
      [
        5522.9,
        471.6
      ],
      [
        5621.6,
        472.4
      ],
      [
        5720.2,
        472.4
      ],
      [
        5818.1,
        472.5
      ],
      [
        5912.0,
        473.2
      ],
      [
        6011.2,
        475.7
      ],
      [
        6110.3,
        474.8
      ],
      [
        6208.8,
        472.5
      ],
      [
        6308.8,
        471.3
      ],
      [
        6406.3,
        468.2
      ],
      [
        6504.7,
        466.4
      ],
      [
        6604.7,
        466.3
      ],
      [
        6701.6,
        466.6
      ],
      [
        6801.0,
        464.5
      ],
      [
        6900.4,
        467.3
      ],
      [
        6999.9,
        469.0
      ],
      [
        7099.8,
        468.1
      ],
      [
        7199.2,
        467.1
      ],
      [
        7298.7,
        466.5
      ],
      [
        7397.7,
        467.0
      ],
      [
        7497.7,
        468.1
      ],
      [
        7597.7,
        468.7
      ],
      [
        7697.6,
        466.1
      ],
      [
        7795.9,
        466.3
      ],
      [
        7895.5,
        467.6
      ],
      [
        7994.6,
        466.7
      ],
      [
        8089.7,
        466.6
      ],
      [
        8188.4,
        467.7
      ],
      [
        8281.1,
        469.7
      ],
      [
        8366.0,
        470.0
      ],
      [
        8457.3,
        470.9
      ],
      [
        8557.2,
        471.9
      ],
      [
        8653.5,
        472.3
      ],
      [
        8750.3,
        474.2
      ],
      [
        8848.7,
        474.5
      ],
      [
        8947.6,
        475.6
      ],
      [
        9046.5,
        475.9
      ],
      [
        9142.0,
        476.4
      ],
      [
        9241.9,
        476.2
      ],
      [
        9340.9,
        474.7
      ],
      [
        9440.2,
        472.6
      ],
      [
        9536.3,
        471.8
      ],
      [
        9630.8,
        471.7
      ],
      [
        9729.9,
        472.3
      ],
      [
        9822.9,
        471.9
      ],
      [
        9922.7,
        469.8
      ],
      [
        10020.9,
        469.8
      ],
      [
        10119.3,
        470.4
      ],
      [
        10219.2,
        472.1
      ],
      [
        10317.9,
        476.1
      ],
      [
        10401.1,
        474.4
      ],
      [
        10500.5,
        474.1
      ],
      [
        10598.7,
        472.9
      ],
      [
        10696.9,
        472.1
      ],
      [
        10792.9,
        471.2
      ],
      [
        10891.8,
        470.9
      ],
      [
        10991.6,
        470.9
      ],
      [
        11091.6,
        470.9
      ],
      [
        11191.6,
        471.5
      ],
      [
        11291.6,
        472.3
      ],
      [
        11391.6,
        472.4
      ],
      [
        11491.6,
        472.4
      ],
      [
        11591.6,
        472.4
      ],
      [
        11691.6,
        471.9
      ],
      [
        11791.6,
        471.0
      ],
      [
        11891.6,
        471.2
      ],
      [
        11991.6,
        471.9
      ],
      [
        12091.6,
        473.2
      ],
      [
        12191.6,
        475.0
      ],
      [
        12291.6,
        474.6
      ],
      [
        12391.6,
        474.0
      ],
      [
        12491.6,
        474.0
      ],
      [
        12591.6,
        474.7
      ],
      [
        12691.6,
        474.2
      ],
      [
        12791.6,
        472.4
      ],
      [
        12891.6,
        472.4
      ],
      [
        12991.6,
        474.6
      ],
      [
        13091.6,
        475.9
      ],
      [
        13191.6,
        474.7
      ],
      [
        13291.6,
        475.2
      ],
      [
        13391.6,
        472.3
      ],
      [
        13491.6,
        472.8
      ],
      [
        13591.6,
        473.0
      ],
      [
        13691.6,
        470.8
      ],
      [
        13791.6,
        469.8
      ],
      [
        13891.6,
        469.7
      ],
      [
        13991.6,
        469.5
      ],
      [
        14091.6,
        469.4
      ],
      [
        14191.6,
        470.6
      ],
      [
        14291.6,
        471.7
      ],
      [
        14391.6,
        472.4
      ],
      [
        14491.6,
        472.0
      ],
      [
        14591.6,
        471.9
      ],
      [
        14691.6,
        473.5
      ],
      [
        14791.6,
        474.9
      ],
      [
        14891.6,
        475.7
      ],
      [
        14991.6,
        473.1
      ],
      [
        15091.6,
        475.6
      ],
      [
        15191.6,
        476.1
      ],
      [
        15291.6,
        475.7
      ],
      [
        15391.6,
        475.5
      ],
      [
        15491.6,
        475.5
      ],
      [
        15591.6,
        475.5
      ],
      [
        15691.6,
        475.5
      ],
      [
        15791.6,
        475.5
      ],
      [
        15891.6,
        475.5
      ],
      [
        15991.6,
        475.5
      ],
      [
        16091.6,
        475.7
      ],
      [
        16191.6,
        476.0
      ],
      [
        16291.6,
        476.3
      ],
      [
        16391.6,
        476.7
      ],
      [
        16491.6,
        477.3
      ],
      [
        16591.6,
        477.8
      ],
      [
        16691.6,
        478.3
      ],
      [
        16791.6,
        478.4
      ],
      [
        16891.6,
        478.4
      ],
      [
        16991.6,
        478.2
      ],
      [
        17091.6,
        478.3
      ],
      [
        17191.6,
        478.5
      ],
      [
        17244.9,
        478.6
      ]
    ],
    "difficulty_estimated": "difficult",
    "surface": [
      "unpaved"
    ],
    "is_loop": false,
    "osm_network_class": null,
    "blaze_color": null,
    "counties": [
      "price"
    ],
    "park": null,
    "managing_authority": "Unknown"
  },
  "editorial": {},
  "derived": {
    "centroid": [
      -90.18510578294608,
      45.89944126252833
    ],
    "bbox": [
      -90.2797428,
      45.8937776,
      -90.0841467,
      45.9096065
    ],
    "drive_minutes_from_wausau": 110,
    "trailhead_coords": null
  }
}