{
  "id": "osmway-horseshoe-trail",
  "name": "Horseshoe Trail",
  "activities": [
    "hiking"
  ],
  "sources": {
    "osm": {
      "way_ids": [
        1190008245,
        1413318180,
        1419255500,
        1419255501,
        1419255503
      ],
      "kind": "named_way",
      "last_fetched": ""
    }
  },
  "geometry": {
    "type": "LineString",
    "coordinates": [
      [
        -88.9691767,
        45.3616124
      ],
      [
        -88.9692152,
        45.3612791
      ],
      [
        -88.9690002,
        45.3610517
      ],
      [
        -88.9688958,
        45.3608258
      ],
      [
        -88.9689039,
        45.3605451
      ],
      [
        -88.9694807,
        45.3605227
      ],
      [
        -88.9698257,
        45.3605037
      ],
      [
        -88.9703325,
        45.3603298
      ],
      [
        -88.9705643,
        45.3602423
      ],
      [
        -88.9709388,
        45.3601011
      ],
      [
        -88.9709256,
        45.3598715
      ],
      [
        -88.9710705,
        45.3595871
      ],
      [
        -88.971371,
        45.3593852
      ],
      [
        -88.9715916,
        45.359168
      ],
      [
        -88.9718176,
        45.3589055
      ],
      [
        -88.9719264,
        45.3585386
      ],
      [
        -88.9719927,
        45.3582261
      ],
      [
        -88.9721649,
        45.3579002
      ],
      [
        -88.9722545,
        45.3575734
      ],
      [
        -88.9724291,
        45.3573188
      ],
      [
        -88.9723017,
        45.3572924
      ],
      [
        -88.9721213,
        45.3572907
      ],
      [
        -88.9720777,
        45.3572744
      ],
      [
        -88.9719836,
        45.3572393
      ],
      [
        -88.9719262,
        45.3571489
      ],
      [
        -88.9717811,
        45.357118
      ],
      [
        -88.9715429,
        45.3571452
      ],
      [
        -88.9713625,
        45.3571825
      ],
      [
        -88.9712055,
        45.3573114
      ],
      [
        -88.9710629,
        45.3574823
      ],
      [
        -88.9709831,
        45.3576208
      ],
      [
        -88.9709317,
        45.3578593
      ],
      [
        -88.9706967,
        45.3580163
      ],
      [
        -88.9704681,
        45.3580882
      ],
      [
        -88.970163,
        45.3581184
      ],
      [
        -88.9698902,
        45.3581121
      ],
      [
        -88.96954,
        45.3581487
      ],
      [
        -88.9693372,
        45.3582572
      ],
      [
        -88.9691213,
        45.3583643
      ],
      [
        -88.9689769,
        45.3584926
      ],
      [
        -88.9687563,
        45.3585566
      ],
      [
        -88.9685143,
        45.3586022
      ],
      [
        -88.9682952,
        45.3585726
      ],
      [
        -88.9681529,
        45.3584418
      ],
      [
        -88.9680341,
        45.3582458
      ],
      [
        -88.9679451,
        45.3580816
      ],
      [
        -88.9677995,
        45.3579758
      ],
      [
        -88.9675893,
        45.3578396
      ],
      [
        -88.9674675,
        45.3580138
      ],
      [
        -88.9673866,
        45.358203
      ],
      [
        -88.967363,
        45.3583853
      ],
      [
        -88.9673535,
        45.3585881
      ],
      [
        -88.9674063,
        45.3587162
      ],
      [
        -88.9673269,
        45.3587015
      ],
      [
        -88.9671791,
        45.3586716
      ],
      [
        -88.9670498,
        45.3585975
      ],
      [
        -88.9669071,
        45.3586065
      ],
      [
        -88.9667361,
        45.3586238
      ],
      [
        -88.9660792,
        45.3586439
      ]
    ]
  },
  "attributes": {
    "length_m": 1350.9,
    "elevation_gain_m": 8.8,
    "elevation_max_m": 477.9,
    "elevation_min_m": 467.6,
    "elevation_profile": [
      [
        0.0,
        477.9
      ],
      [
        96.0,
        476.6
      ],
      [
        177.1,
        476.5
      ],
      [
        274.4,
        475.6
      ],
      [
        369.5,
        474.9
      ],
      [
        467.7,
        475.0
      ],
      [
        567.3,
        476.3
      ],
      [
        634.9,
        469.5
      ],
      [
        726.0,
        468.0
      ],
      [
        816.3,
        467.9
      ],
      [
        912.4,
        467.6
      ],
      [
        993.8,
        473.6
      ],
      [
        1044.7,
        474.5
      ],
      [
        1103.7,
        475.0
      ],
      [
        1157.0,
        471.7
      ]
    ],
    "difficulty_estimated": "easy",
    "surface": [
      "ground"
    ],
    "is_loop": false,
    "osm_network_class": null,
    "blaze_color": null,
    "counties": [
      "langlade"
    ],
    "park": null,
    "managing_authority": "Unknown"
  },
  "editorial": {},
  "derived": {
    "centroid": [
      -88.96982288971098,
      45.35880579257948
    ],
    "bbox": [
      -88.9724291,
      45.357118,
      -88.9660792,
      45.3616124
    ],
    "drive_minutes_from_wausau": 66,
    "trailhead_coords": null
  }
}